burpy/__init__.py
burpy/context/__init__.py
burpy/context/ctx.py
burpy/core/burpy.py
burpy/flag/__init__.py
burpy/flag/flags.py
burpy/text/__init__.py
burpy/text/enum.py
burpy/text/formatting.py
burpy_cli-0.1.2.dist-info/LICENSE
burpy_cli-0.1.2.dist-info/METADATA
burpy_cli-0.1.2.dist-info/WHEEL
burpy_cli-0.1.2.dist-info/entry_points.txt
burpy_cli-0.1.2.dist-info/RECORD
