Metadata-Version: 2.1
Name: burpy-cli
Version: 0.1.2
Summary: A rich tool to create CLI application in python with ease and almost zero dependency on third party packages
License: MIT
Keywords: cli,command-line,framework,python
Author: MukundSinghRajput
Author-email: mukundsrajput@gmail.com
Requires-Python: >=3.9
Classifier: Development Status :: 3 - Alpha
Classifier: Intended Audience :: Developers
Classifier: License :: OSI Approved :: MIT License
Classifier: Programming Language :: Python :: 3
Classifier: Programming Language :: Python :: 3.9
Classifier: Programming Language :: Python :: 3.10
Classifier: Programming Language :: Python :: 3.11
Classifier: Programming Language :: Python :: 3.12
Classifier: Programming Language :: Python :: 3.13
Classifier: Topic :: Software Development :: Libraries :: Python Modules
Classifier: Topic :: Utilities
Project-URL: Bug Tracker, https://github.com/MukundSinghRajput/burpy-cli/issues
Project-URL: Homepage, https://github.com/MukundSinghRajput/burpy-cli
